[
    {
        "lang": "en",
        "hits": [
            {
                "type": "translation",
                "opendict": false,
                "source": "<span class=\"example\">I feel <strong class=\"tilde\">at</strong> ease</span>",
                "target": "mi sento a mio agio"
            },
            {
                "type": "translation",
                "opendict": false,
                "source": "<span class=\"example\">I feel I don&#39;t <strong class=\"tilde\">belong</strong> here</span>",
                "target": "non mi sento a mio agio qui"
            }
        ]
    }
]