[
    {
        "lang": "it",
        "hits": [
            {
                "type": "entry",
                "opendict": false,
                "roms": [
                    {
                        "headword": "bellezza",
                        "headword_full": "bellezza    <span class=\"phonetics\">[bel<span class=\"separator\">·</span>ˈlet<span class=\"separator\">·</span>tsa]</span> <span class=\"wordclass\"><acronym title=\"noun\">N</acronym></span> <span class=\"genus\"><acronym title=\"feminine\">f</acronym></span>",
                        "wordclass": "noun",
                        "arabs": [
                            {
                                "header": "1. bellezza <span class=\"sense\">(qualità, persona)</span>:",
                                "translations": [
                                    {
                                        "source": "<strong class=\"headword\">bellezza</strong>",
                                        "target": "beauty"
                                    },
                                    {
                                        "source": "<span class=\"example\">istituto di <strong class=\"tilde\">bellezza</strong></span>",
                                        "target": "beauty parlor"
                                    },
                                    {
                                        "source": "<span class=\"example\">prodotti di <strong class=\"tilde\">bellezza</strong></span>",
                                        "target": "beauty products"
                                    },
                                    {
                                        "source": "<span class=\"example\">per <strong class=\"tilde\">bellezza</strong></span>",
                                        "target": "to look good"
                                    },
                                    {
                                        "source": "<span class=\"example\">le -e di Siena</span>",
                                        "target": "the sights of Siena"
                                    },
                                    {
                                        "source": "<span class=\"example\">le -e della natura</span>",
                                        "target": "the beauties of nature"
                                    },
                                    {
                                        "source": "<span class=\"example\">concorso di <strong class=\"tilde\">bellezza</strong></span>",
                                        "target": "beauty competition"
                                    }
                                ]
                            },
                            {
                                "header": "2. bellezza <span class=\"sense\">(<acronym title=\"phrase, idiom\">phrase</acronym>)</span>:",
                                "translations": [
                                    {
                                        "source": "<span class=\"example\">che <strong class=\"tilde\">bellezza!</strong></span>",
                                        "target": "wonderful!"
                                    },
                                    {
                                        "source": "<span class=\"example\">per finire in <strong class=\"tilde\">bellezza</strong></span> <span class=\"rhetoric\"><acronym title=\"figurative\">fig</acronym></span>",
                                        "target": "to round (<acronym title=\"something\">sth</acronym>) off nicely"
                                    },
                                    {
                                        "source": "<span class=\"example\">la <strong class=\"tilde\">bellezza</strong> di tremila euro</span> <span class=\"style\"><acronym title=\"informal\">inf</acronym></span>",
                                        "target": "the princely sum of three thousand euros"
                                    }
                                ]
                            }
                        ]
                    }
                ]
            }
        ]
    }
]