[
    {
        "lang": "it",
        "hits": [
            {
                "type": "entry",
                "opendict": false,
                "roms": [
                    {
                        "headword": "caccia",
                        "headword_full": "caccia<sup>1</sup>   <span class=\"flexion\">&lt;-cce&gt;</span>  <span class=\"phonetics\">[ˈkat<span class=\"separator\">·</span>tʃa]</span> <span class=\"wordclass\"><acronym title=\"noun\">N</acronym></span> <span class=\"genus\"><acronym title=\"feminine\">f</acronym></span>",
                        "wordclass": "noun",
                        "arabs": [
                            {
                                "header": "1. caccia <span class=\"sense\">(arte venatoria)</span>:",
                                "translations": [
                                    {
                                        "source": "<strong class=\"headword\">caccia</strong>",
                                        "target": "hunting"
                                    },
                                    {
                                        "source": "<span class=\"example\"><strong class=\"tilde\">caccia</strong> alla lepre</span>",
                                        "target": "open field coursing"
                                    },
                                    {
                                        "source": "<span class=\"example\"><strong class=\"tilde\">caccia</strong> grossa</span>",
                                        "target": "big game hunting"
                                    },
                                    {
                                        "source": "<span class=\"example\">cane da <strong class=\"tilde\">caccia</strong></span>",
                                        "target": "hunting dog"
                                    },
                                    {
                                        "source": "<span class=\"example\">andare a <strong class=\"tilde\">caccia</strong></span>",
                                        "target": "to go hunting"
                                    }
                                ]
                            },
                            {
                                "header": "2. caccia <span class=\"sense\">(inseguimento)</span>:",
                                "translations": [
                                    {
                                        "source": "<strong class=\"headword\">caccia</strong>",
                                        "target": "hunt"
                                    },
                                    {
                                        "source": "<span class=\"example\">aereo da <strong class=\"tilde\">caccia</strong></span>",
                                        "target": "fighter (plane)"
                                    },
                                    {
                                        "source": "<span class=\"example\">dare la <strong class=\"tilde\">caccia</strong> a <acronym title=\"qualcuno\">qu</acronym></span>",
                                        "target": "to hunt <acronym title=\"somebody\">sb</acronym>"
                                    }
                                ]
                            },
                            {
                                "header": "3. caccia <span class=\"sense\">(ricerca)</span>:",
                                "translations": [
                                    {
                                        "source": "<strong class=\"headword\">caccia</strong>",
                                        "target": "search"
                                    },
                                    {
                                        "source": "<span class=\"example\">a <strong class=\"tilde\">caccia</strong> di guai</span>",
                                        "target": "looking for trouble"
                                    }
                                ]
                            }
                        ]
                    }
                ]
            },
            {
                "type": "entry",
                "opendict": false,
                "roms": [
                    {
                        "headword": "caccia",
                        "headword_full": "caccia<sup>2</sup>   <span class=\"flexion\">&lt;-&gt;</span>  <span class=\"wordclass\"><acronym title=\"noun\">N</acronym></span> <span class=\"genus\"><acronym title=\"masculine\">m</acronym></span>",
                        "wordclass": "noun",
                        "arabs": [
                            {
                                "header": "1. caccia <span class=\"topic\"><acronym title=\"aviation\">AVIAT</acronym></span>:",
                                "translations": [
                                    {
                                        "source": "<strong class=\"headword\">caccia</strong>",
                                        "target": "fighter (plane)"
                                    }
                                ]
                            },
                            {
                                "header": "2. caccia <span class=\"topic\"><acronym title=\"nautical, naval\">NAUT</acronym></span>:",
                                "translations": [
                                    {
                                        "source": "<strong class=\"headword\">caccia</strong>",
                                        "target": "destroyer"
                                    }
                                ]
                            }
                        ]
                    }
                ]
            }
        ]
    }
]