[
    {
        "lang": "it",
        "hits": [
            {
                "type": "entry",
                "opendict": false,
                "roms": [
                    {
                        "headword": "divieto",
                        "headword_full": "divieto <span class=\"phonetics\">[di<span class=\"separator\">·</span>ˈviɛ:<span class=\"separator\">·</span>to]</span> <span class=\"wordclass\"><acronym title=\"noun\">N</acronym></span> <span class=\"genus\"><acronym title=\"masculine\">m</acronym></span>",
                        "wordclass": "noun",
                        "arabs": [
                            {
                                "header": "",
                                "translations": [
                                    {
                                        "source": "<strong class=\"headword\">divieto</strong>",
                                        "target": "prohibition"
                                    },
                                    {
                                        "source": "<span class=\"example\">il <strong class=\"tilde\">divieto</strong> di fumare in locali pubblici</span>",
                                        "target": "the ban on smoking in public places"
                                    },
                                    {
                                        "source": "<span class=\"example\"><strong class=\"tilde\">‘divieto</strong> di parcheggio’</span>",
                                        "target": "‘No parking’"
                                    },
                                    {
                                        "source": "<span class=\"example\"><strong class=\"tilde\">‘divieto</strong> di sosta’</span>",
                                        "target": "‘No waiting’"
                                    },
                                    {
                                        "source": "<span class=\"example\"><strong class=\"tilde\">‘divieto</strong> di transito’</span>",
                                        "target": "‘No entry’"
                                    }
                                ]
                            }
                        ]
                    }
                ]
            }
        ]
    }
]