[
    {
        "lang": "it",
        "hits": [
            {
                "type": "entry",
                "opendict": false,
                "roms": [
                    {
                        "headword": "onda",
                        "headword_full": "onda <span class=\"phonetics\">[ˈon<span class=\"separator\">·</span>da]</span> <span class=\"wordclass\"><acronym title=\"noun\">N</acronym></span> <span class=\"genus\"><acronym title=\"feminine\">f</acronym></span>",
                        "wordclass": "noun",
                        "arabs": [
                            {
                                "header": "1. onda <span class=\"sense\">(del mare)</span>:",
                                "translations": [
                                    {
                                        "source": "<strong class=\"headword\">onda</strong>",
                                        "target": "wave"
                                    },
                                    {
                                        "source": "<span class=\"example\">essere sulla cresta <strong class=\"tilde\">dell&#39;onda</strong></span> <span class=\"rhetoric\"><acronym title=\"figurative\">fig</acronym></span>",
                                        "target": "to be riding on the crest of a wave"
                                    }
                                ]
                            },
                            {
                                "header": "2. onda <span class=\"topic\"><acronym title=\"physics\">PHYS</acronym></span>:",
                                "translations": [
                                    {
                                        "source": "<strong class=\"headword\">onda</strong>",
                                        "target": "wave"
                                    },
                                    {
                                        "source": "<span class=\"example\">-e corte/lunghe/medie</span>",
                                        "target": "short/long/medium waves"
                                    },
                                    {
                                        "source": "<span class=\"example\"><strong class=\"tilde\">onda</strong> d&#39;urto</span>",
                                        "target": "shockwave"
                                    },
                                    {
                                        "source": "<span class=\"example\">andare in <strong class=\"tilde\">onda</strong></span> <span class=\"topic\"><acronym title=\"television\">TV</acronym>, <acronym title=\"radio broadcasting\">RADIO</acronym></span>",
                                        "target": "to be broadcast"
                                    },
                                    {
                                        "source": "<span class=\"example\">mandare in <strong class=\"tilde\">onda</strong></span> <span class=\"topic\"><acronym title=\"television\">TV</acronym>, <acronym title=\"radio broadcasting\">RADIO</acronym></span>",
                                        "target": "to broadcast"
                                    }
                                ]
                            },
                            {
                                "header": "3. onda <span class=\"sense\">(<acronym title=\"phrase, idiom\">phrase</acronym>)</span>:",
                                "translations": [
                                    {
                                        "source": "<span class=\"example\"><strong class=\"tilde\">onda</strong> verde</span> <span class=\"topic\">alla <acronym title=\"radio broadcasting\">RADIO</acronym></span>",
                                        "target": "travel bulletin"
                                    },
                                    {
                                        "source": "<span class=\"example\"><strong class=\"tilde\">onda</strong> verde</span> <span class=\"sense\">(semafori)</span>",
                                        "target": "synchronized traffic lights"
                                    }
                                ]
                            }
                        ]
                    }
                ]
            }
        ]
    }
]