[
    {
        "lang": "it",
        "hits": [
            {
                "type": "entry",
                "opendict": false,
                "roms": [
                    {
                        "headword": "rilegare",
                        "headword_full": "rilegare <span class=\"phonetics\">[ri<span class=\"separator\">·</span>le<span class=\"separator\">·</span>ˈga:<span class=\"separator\">·</span>re]</span> <span class=\"wordclass\"><acronym title=\"verb\">VB</acronym></span> <span class=\"verbclass\"><acronym title=\"transitive verb\">trans</acronym></span> <span class=\"sense\">(libro)</span>",
                        "wordclass": "transitive verb",
                        "arabs": [
                            {
                                "header": "",
                                "translations": [
                                    {
                                        "source": "<strong class=\"headword\">rilegare</strong>",
                                        "target": "to bind"
                                    }
                                ]
                            }
                        ]
                    }
                ]
            }
        ]
    }
]