[
    {
        "lang": "en",
        "hits": [
            {
                "type": "translation",
                "opendict": false,
                "source": "<strong class=\"headword\">repeatedly</strong>",
                "target": "ripetutamente"
            },
            {
                "type": "translation",
                "opendict": false,
                "source": "<strong class=\"headword\">harass</strong>",
                "target": "attaccare ripetutamente"
            }
        ]
    }
]