[
    {
        "lang": "it",
        "hits": [
            {
                "type": "entry",
                "opendict": false,
                "roms": [
                    {
                        "headword": "sopravvivere",
                        "headword_full": "sopravvivere <span class=\"phonetics\">[sop<span class=\"separator\">·</span>rav<span class=\"separator\">·</span>ˈvi:<span class=\"separator\">·</span>ve<span class=\"separator\">·</span>re]</span> <span class=\"wordclass\"><acronym title=\"verb\">VB</acronym></span> <span class=\"verbclass\"><acronym title=\"intransitive verb\">intr</acronym></span> <span class=\"auxiliary_verb\">+essere</span>",
                        "wordclass": "intransitive verb",
                        "arabs": [
                            {
                                "header": "1. sopravvivere <span class=\"sense\">(a persone, a disgrazia)</span>:",
                                "translations": [
                                    {
                                        "source": "<span class=\"example\"><strong class=\"tilde\">sopravvivere</strong> a <acronym title=\"qualcuno\">qu</acronym></span>",
                                        "target": "to outlive <acronym title=\"somebody\">sb</acronym>"
                                    },
                                    {
                                        "source": "<span class=\"example\"><strong class=\"tilde\">sopravvivere</strong> a <acronym title=\"qualcosa\">qc</acronym></span>",
                                        "target": "to survive <acronym title=\"something\">sth</acronym>"
                                    }
                                ]
                            },
                            {
                                "header": "2. sopravvivere <span class=\"rhetoric\"><acronym title=\"figurative\">fig</acronym></span> <span class=\"sense\">(ricordo)</span>:",
                                "translations": [
                                    {
                                        "source": "<strong class=\"headword\">sopravvivere</strong>",
                                        "target": "to live on"
                                    }
                                ]
                            }
                        ]
                    }
                ]
            }
        ]
    }
]