[
    {
        "lang": "it",
        "hits": [
            {
                "type": "entry",
                "opendict": false,
                "roms": [
                    {
                        "headword": "tracciare",
                        "headword_full": "tracciare <span class=\"phonetics\">[trat<span class=\"separator\">·</span>ˈtʃa:<span class=\"separator\">·</span>re]</span> <span class=\"wordclass\"><acronym title=\"verb\">VB</acronym></span> <span class=\"verbclass\"><acronym title=\"transitive verb\">trans</acronym></span>",
                        "wordclass": "transitive verb",
                        "arabs": [
                            {
                                "header": "1. tracciare <span class=\"sense\">(linea, quadrato)</span>:",
                                "translations": [
                                    {
                                        "source": "<strong class=\"headword\">tracciare</strong>",
                                        "target": "to draw"
                                    }
                                ]
                            },
                            {
                                "header": "2. tracciare <span class=\"sense\">(strade, ferrovie)</span>:",
                                "translations": [
                                    {
                                        "source": "<strong class=\"headword\">tracciare</strong>",
                                        "target": "to mark out"
                                    }
                                ]
                            },
                            {
                                "header": "3. tracciare <span class=\"rhetoric\"><acronym title=\"figurative\">fig</acronym></span> <span class=\"sense\">(discorso, lettera)</span>:",
                                "translations": [
                                    {
                                        "source": "<strong class=\"headword\">tracciare</strong>",
                                        "target": "to draft"
                                    }
                                ]
                            }
                        ]
                    }
                ]
            }
        ]
    }
]